frosty/__init__.py
frosty/compat.py
frosty/freezers.py
frosty/includes.py
frosty-0.1.8.dist-info/DESCRIPTION.rst
frosty-0.1.8.dist-info/METADATA
frosty-0.1.8.dist-info/metadata.json
frosty-0.1.8.dist-info/RECORD
frosty-0.1.8.dist-info/top_level.txt
frosty-0.1.8.dist-info/WHEEL
