Metadata-Version: 2.0
Name: frosty
Version: 0.1.8
Summary: Frosty is a collection of utilities for working with frozen packages.
Home-page: https://github.com/dmckeone/frosty
Author: David McKeone
Author-email: davidmckeone@gmail.com
License: BSD
Download-URL: https://github.com/dmckeone/Frosty/tarball/0.1.8
Keywords: frosty,frozen,esky,py2app,py2exe,bbfreeze,cxfreeze,utilities
Platform: UNKNOWN
Classifier: Development Status :: 2 - Pre-Alpha
Classifier: Intended Audience :: Developers
Classifier: License :: OSI Approved :: BSD License
Classifier: Natural Language :: English
Classifier: Programming Language :: Python :: 2
Classifier: Programming Language :: Python :: 2.6
Classifier: Programming Language :: Python :: 2.7
Classifier: Programming Language :: Python :: 3
Classifier: Programming Language :: Python :: 3.3
Classifier: Programming Language :: Python :: 3.4
Requires-Dist: six
Requires-Dist: wheel
